py_dict_comparing_xethhung12/__init__.py
py_dict_comparing_xethhung12/__main__.py
py_dict_comparing_xethhung12/_module_comparing.py
py_dict_comparing_xethhung12/_module_csv.py
py_dict_comparing_xethhung12/_cmd/run.py
py_dict_comparing_xethhung12-0.0.31.dist-info/METADATA
py_dict_comparing_xethhung12-0.0.31.dist-info/WHEEL
py_dict_comparing_xethhung12-0.0.31.dist-info/licenses/LICENSE
py_dict_comparing_xethhung12-0.0.31.dist-info/RECORD
